project_phoenix/__init__.py
project_phoenix/cmd.py
project_phoenix/git.py
project_phoenix/py3.py
project_phoenix-2023.9.9.dist-info/LICENSE
project_phoenix-2023.9.9.dist-info/METADATA
project_phoenix-2023.9.9.dist-info/WHEEL
project_phoenix-2023.9.9.dist-info/entry_points.txt
project_phoenix-2023.9.9.dist-info/RECORD
