Metadata-Version: 2.1
Name: project_phoenix
Version: 2023.9.9
Summary: Git tools
Home-page: https://pypi.org/project/project-phoenix/
License: MIT
Keywords: git,git pull,git config,pip,pip update
Author: walchko
Author-email: walchko@users.noreply.github.com
Requires-Python: >=3.9
Classifier: Development Status :: 4 - Beta
Classifier: Intended Audience :: Developers
Classifier: License :: OSI Approved :: MIT License
Classifier: Operating System :: OS Independent
Classifier: Programming Language :: Python :: 3
Classifier: Programming Language :: Python :: 3.9
Classifier: Programming Language :: Python :: 3.10
Classifier: Programming Language :: Python :: 3.11
Classifier: Topic :: Software Development :: Libraries
Classifier: Topic :: Software Development :: Libraries :: Application Frameworks
Classifier: Topic :: Software Development :: Libraries :: Python Modules
Requires-Dist: colorama
Project-URL: Repository, http://github.com/walchko/project-phoenix
